frasco_sentry.py
setup.py
frasco_sentry.egg-info/PKG-INFO
frasco_sentry.egg-info/SOURCES.txt
frasco_sentry.egg-info/dependency_links.txt
frasco_sentry.egg-info/not-zip-safe
frasco_sentry.egg-info/requires.txt
frasco_sentry.egg-info/top_level.txt