Metadata-Version: 1.0
Name: frasco-sentry
Version: 0.1
Summary: Sentry integration for Frasco
Home-page: http://github.com/frascoweb/frasco-sentry
Author: Maxime Bouroumeau-Fuseau
Author-email: maxime.bouroumeau@gmail.com
License: MIT
Platform: any
